Metadata-Version: 1.0
Name: Trumping
Version: 0.1
Summary: Advanced Truncation
Home-page: UNKNOWN
Author: UNKNOWN
Author-email: igr.tkchv@gmail.com
License: UNKNOWN
Platform: UNKNOWN
